protobus_server/__init__.py
protobus_server/main.py
protobus_server/service.py
protobus_server/utilities.py
protobus_server/idl/__init__.py
protobus_server/idl/protobus_event_pb2.py
protobus_server/idl/protobus_event_pb2_grpc.py
protobus_server/idl/protobus_rpc_pb2.py
protobus_server/idl/protobus_rpc_pb2_grpc.py
protobus_server-0.1.4.dist-info/LICENSE
protobus_server-0.1.4.dist-info/METADATA
protobus_server-0.1.4.dist-info/WHEEL
protobus_server-0.1.4.dist-info/entry_points.txt
protobus_server-0.1.4.dist-info/top_level.txt
protobus_server-0.1.4.dist-info/RECORD
