Metadata-Version: 2.1
Name: protobus-server
Version: 0.1.4
Summary: A minimalistic daemon providing a partitioned log message bus.
Home-page: https://github.com/protobus/protobus-server
Author: The protobus developers
Author-email: protobus-dev@googlegroups.com
Maintainer: Felix Werner
Maintainer-email: protobus-maintainers@googlegroups.com
License: MIT/Apache-2.0
Platform: UNKNOWN
Classifier: Development Status :: 1 - Planning
Classifier: Programming Language :: Python :: 3
Classifier: License :: OSI Approved :: Apache Software License
Requires-Python: >=3.6
Requires-Dist: grpcio (<=1.31,>=1.30.0)
